{"rows":[{"Id":"1","name":"Hola Hola Hola 1","company":"ARCHYSOFT","curp":"akpg941030mbfdlb09"},{"Id":"2","name":"Hola Hola Hola 2","company":"ARCHYSOFT","curp":"akpg941030mbfdlb10"},{"Id":"3","name":"Hola Hola Hola 3","company":"ARCHYSOFT","curp":"akpg941030mbfdlb11"},{"Id":"4","name":"Hola Hola Hola 4","company":"ARCHYSOFT","curp":"akpg941030mbfdlb12"},{"Id":"5","name":"Hola Hola Hola 5","company":"ARCHYSOFT","curp":"akpg941030mbfdlb13"},{"Id":"6","name":"Hola Hola Hola 6","company":"ARCHYSOFT","curp":"akpg941030mbfdlb14"},{"Id":"7","name":"Hola Hola Hola 7","company":"ARCHYSOFT","curp":"akpg941030mbfdlb15"},{"Id":"8","name":"Hola Hola Hola 8","company":"ARCHYSOFT","curp":"akpg941030mbfdlb16"},{"Id":"9","name":"Hola Hola Hola 9","company":"ARCHYSOFT","curp":"akpg941030mbfdlb17"},{"Id":"10","name":"Hola Hola Hola 10","company":"ARCHYSOFT","curp":"akpg941030mbfdlb18"},{"Id":"11","name":"Hola Hola Hola 11","company":"ARCHYSOFT","curp":"akpg941030mbfdlb19"},{"Id":"12","name":"Hola Hola Hola 12","company":"ARCHYSOFT","curp":"akpg941030mbfdlb20"},{"Id":"13","name":"Hola Hola Hola 13","company":"ARCHYSOFT","curp":"akpg941030mbfdlb21"},{"Id":"14","name":"Hola Hola Hola 14","company":"ARCHYSOFT","curp":"akpg941030mbfdlb22"},{"Id":"15","name":"Hola Hola Hola 15","company":"ARCHYSOFT","curp":"akpg941030mbfdlb23"},{"Id":"16","name":"gfg","company":"gfgf","curp":"gffgfg"},{"Id":"17","name":"gfgfg","company":"gfgfgf","curp":"gfgfggfgfgf"},{"Id":"18","name":"trtrt","company":"trtrt","curp":"wweew"},{"Id":"19","name":"","company":"","curp":""},{"Id":"20","name":"","company":"","curp":""},{"Id":"21","name":"","company":"","curp":""},{"Id":"22","name":"","company":"","curp":""},{"Id":"23","name":"","company":"","curp":""},{"Id":"24","name":"","company":"","curp":""},{"Id":"25","name":"","company":"","curp":""},{"Id":"26","name":"","company":"","curp":""},{"Id":"27","name":"","company":"","curp":""},{"Id":"28","name":"","company":"","curp":""},{"Id":"29","name":"","company":"","curp":""},{"Id":"30","name":"","company":"","curp":""},{"Id":"31","name":"","company":"","curp":""},{"Id":"32","name":"","company":"","curp":""},{"Id":"33","name":"","company":"","curp":""},{"Id":"34","name":"","company":"","curp":""},{"Id":"35","name":"","company":"","curp":""},{"Id":"36","name":"","company":"","curp":""},{"Id":"37","name":"","company":"","curp":""},{"Id":"38","name":"","company":"","curp":""},{"Id":"39","name":"","company":"","curp":""},{"Id":"40","name":"","company":"","curp":""},{"Id":"41","name":"","company":"","curp":""},{"Id":"42","name":"","company":"","curp":""},{"Id":"43","name":"","company":"","curp":""},{"Id":"44","name":"","company":"","curp":""},{"Id":"45","name":"","company":"","curp":""},{"Id":"46","name":"","company":"","curp":""},{"Id":"47","name":"","company":"","curp":""},{"Id":"48","name":"","company":"","curp":""},{"Id":"49","name":"","company":"","curp":""},{"Id":"50","name":"","company":"","curp":""}]}